Metadata-Version: 2.1
Name: atto
Version: 1.1.8
Summary: Simple curses text editor
Home-page: https://github.com/jenca-adam/atto/
Author: Adam Jenca
Author-email: jenca.adam@gmail.com
License: UNKNOWN
Platform: UNKNOWN
Classifier: Development Status :: 4 - Beta
Classifier: Environment :: Console :: Curses
Classifier: Intended Audience :: End Users/Desktop
Classifier: License :: OSI Approved :: GNU General Public License (GPL)
Classifier: Operating System :: OS Independent
Classifier: Programming Language :: Python :: 3
Classifier: Topic :: Text Editors
License-File: LICENSE
